<?xml version="1.0" encoding="UTF-8"?>
<!--
To change this license header, choose License Headers in Project Properties.
To change this template file, choose Tools | Templates
and open the template in the editor.
-->
<ayudantes>
    <ayudante tipo="varias">
        <nombre>Mayra Alejandra Moreira Solorzano</nombre>
        <descripcion>Ayudante de laboratorios de la FIEC</descripcion>
        <email>mmoreira@espol.edu.ec</email>
        <carga>10</carga>
    </ayudante>
    <ayudante tipo="varias">
        <nombre>Xavier Agustin Villacres Ventura</nombre>
        <descripcion>Ayudante del Departamento de Soporte Técnico de la FIEC</descripcion>
        <email>xvillacres@espol.edu.ec</email>
        <carga>10</carga>
    </ayudante>
    <ayudante tipo="academico">
        <nombre>Juan Manuel Romero</nombre>
        <descripcion>Ayudante del curso de Ingeniería de Software I</descripcion>
        <email>jromero@espol.edu.ec</email>
        <carga>5</carga>
    </ayudante>
</ayudantes>
